cryptopanic/__init__.py
cryptopanic/client.py
cryptopanic/exceptions.py
cryptopanic/models.py
cryptopanic-0.1.0.dist-info/licenses/LICENSE
cryptopanic-0.1.0.dist-info/METADATA
cryptopanic-0.1.0.dist-info/WHEEL
cryptopanic-0.1.0.dist-info/top_level.txt
cryptopanic-0.1.0.dist-info/RECORD
