Metadata-Version: 2.4
Name: cryptopanic
Version: 0.1.0
Summary: A Python client library for the CryptoPanic API
Author-email: Erwin Lejeune <rangonomics@gmail.com>
License: MIT
Project-URL: Homepage, https://github.com/guilyx/cryptopanic
Project-URL: Documentation, https://github.com/guilyx/cryptopanic#readme
Project-URL: Repository, https://github.com/guilyx/cryptopanic
Project-URL: Issues, https://github/guilyx/cryptopanic/issues
Keywords: cryptopanic,crypto,news,api,cryptocurrency
Classifier: Development Status :: 4 - Beta
Classifier: Intended Audience :: Developers
Classifier: License :: OSI Approved :: MIT License
Classifier: Programming Language :: Python :: 3
Classifier: Programming Language :: Python :: 3.8
Classifier: Programming Language :: Python :: 3.9
Classifier: Programming Language :: Python :: 3.10
Classifier: Programming Language :: Python :: 3.11
Classifier: Programming Language :: Python :: 3.12
Classifier: Topic :: Software Development :: Libraries :: Python Modules
Requires-Python: >=3.8
License-File: LICENSE
Requires-Dist: requests>=2.31.0
Requires-Dist: pydantic>=2.0.0
Provides-Extra: dev
Requires-Dist: pytest>=7.4.0; extra == "dev"
Requires-Dist: pytest-cov>=4.1.0; extra == "dev"
Requires-Dist: pytest-mock>=3.11.0; extra == "dev"
Requires-Dist: black>=23.0.0; extra == "dev"
Requires-Dist: ruff>=0.1.0; extra == "dev"
Requires-Dist: mypy>=1.5.0; extra == "dev"
Requires-Dist: pre-commit>=3.4.0; extra == "dev"
Requires-Dist: types-requests>=2.31.0; extra == "dev"
Dynamic: license-file
